{
  "productos": [
    {
      "id": 1,
      "nombre": "Zumo de Zanahoria",
      "precio": "31111"
    },
    {
      "id": 2,
      "nombre": "Zumo de Naranja",
      "precio": "1"
    },
    {
      "nombre": "Zumo de Naranja",
      "precio": "300",
      "id": 3
    },
    {
      "nombre": "Rib Eye 800g",
      "precio": "200",
      "id": 4
    },
    {
      "nombre": "Zumo de Fresa",
      "precio": "200",
      "id": 5
    },
    {
      "nombre": "Pollo",
      "precio": 3455,
      "id": 6
    },
    {
      "nombre": "Riby",
      "precio": 400,
      "id": 7
    },
    {
      "nombre": "Hamburguesa vegana",
      "precio": 123,
      "id": 8
    },
    {
      "nombre": "Carne Wagyú",
      "precio": 234,
      "id": 9
    }
  ]
}